{
   "rps": {
      "0": [
         "Wow! You're so good you beat a robot!",
         "Hey! You finally won for ounce!",
         "The people that thought robots will take over the world.",
         "Never give up!",
         "Robot mind reader.",
         "Yeah, I'm special."
      ],
      "1": [
         "Hey, at least you didn't lose.",
         "Phew, that was close.",
         "Let's not try that again.",
         "Boring."
      ],
      "2": [
         "How did you lose to a robot?",
         "Hey, did you know if you stop playing you will stop losing?",
         "Oh come on!",
         "So close!",
         "I hate robots anyway."
      ]
   },
   "beg": {
      "success": [
         "Oh, the poor thing, here, have ${money}.",
         "Have ${money}, it's the least I can do.",
         "You begged and got ${money}.",
         "**Elon Musk**: Here, have ${money}.",
         "**Jeff Bezos**: Here is ${money}, go spend it on Amazon."
      ],
      "fail": [
         "Go beg somewhere else.",
         "Sorry, I didn't bring my wallet.",
         "Go get a job for ounce.",
         "Imagine begging lol."
      ]
   },
   "search": {
      "success": [
         "You searched high and low and found ${money}.",
         "After looking a bit you found a wallet with ${money} in it!",
         "You found ${money}. Maybe try searching there again."
      ],
      "fail": [
         "You searched and found nothing, amazing!",
         "You found nothing lol.",
         "Imagine failing to find something."
      ]
   }
}